rna_torsionbert/__init__.py
rna_torsionbert/py.typed
rna_torsionbert/rna_torsionBERT_cli.py
rna_torsionbert/tb_mcq_cli.py
rna_torsionbert/utils.py
rna_torsionbert/enums/__init__.py
rna_torsionbert/enums/atoms.py
rna_torsionbert/helper/__init__.py
rna_torsionbert/helper/computation_helper.py
rna_torsionbert/helper/extractor_helper.py
rna_torsionbert/helper/rna_torsionBERT_helper.py
rna_torsionbert/metrics/__init__.py
rna_torsionbert/metrics/mcq.py
rna_torsionbert-0.1.4.dist-info/METADATA
rna_torsionbert-0.1.4.dist-info/WHEEL
rna_torsionbert-0.1.4.dist-info/entry_points.txt
rna_torsionbert-0.1.4.dist-info/RECORD
