Metadata-Version: 2.4
Name: rna-torsionbert
Version: 0.1.4
Summary: Add your description here
Author-email: clementbernardd <clementbernardd@gmail.com>
Requires-Python: >=3.10
Requires-Dist: biopython>=1.85
Requires-Dist: loguru>=0.7.3
Requires-Dist: numpy<2.0
Requires-Dist: pandas>=2.2.3
Requires-Dist: scipy>=1.15.2
Requires-Dist: torch>=2.0.1
Requires-Dist: transformers>=4.49.0
